{
	"swagger": "2.0",
	"info": {
		"title": "cowquake API",
		"description": "This is an cowquakeAPI, which is part of the English Language API Recipe Book.",
		"termsOfService": "http://apievangelist.com/terms-of-service.html",
		"version": "v1"
	},
	"host": "c.example.com",
	"basePath": "/",
	"schemes": ["http"],
	"produces": ["application/json"],
	"paths": {
		"/cowquake/": {
			"get": {
				"summary": "cowquake item",
				"description": "returns an cowquake item",
				"operationId": "getcowquake",
				"parameters": [{
					"name": "q",
					"in": "query",
					"description": "Keyword search for item",
					"required": false,
					"type": "string"
				}],
				"responses": {
					"200": {
						"description": "A successful response.",
						"schema": {
							"type": "array",
							"items": {
								"$ref": "#/definitions/item"
							}
						}
					}
				},
				"tags": ["cowquake"]
			},
			"post": {
				"summary": "cowquake item",
				"description": "adds an cowquake item",
				"operationId": "addcowquake",
				"parameters": [{
					"name": "name",
					"in": "formData",
					"description": "Name of item",
					"required": true,
					"type": "string"
				},
				{
					"name": "description",
					"in": "formData",
					"description": "Description of item",
					"required": true,
					"type": "string"
				}],
				"responses": {
					"200": {
						"description": "A successful response.",
						"schema": {
							"type": "array",
							"items": {
								"$ref": "#/definitions/item"
							}
						}
					}
				},
				"tags": ["cowquake"]
			}
		},
		"/cowquake/{id}/": {
			"get": {
				"summary": "cowquake item",
				"description": "returns a single cowquake item",
				"operationId": "getcowquakeItem",
				"parameters": [{
					"name": "id",
					"in": "path",
					"description": "Unique id for item",
					"required": true,
					"type": "integer"
				}],
				"responses": {
					"200": {
						"description": "A successful response.",
						"schema": {
							"type": "array",
							"items": {
								"$ref": "#/definitions/item"
							}
						}
					}
				},
				"tags": ["cowquake"]
			},
			"put": {
				"summary": "cowquake item",
				"description": "update a single cowquake item",
				"operationId": "updatecowquakeItem",
				"parameters": [{
					"name": "id",
					"in": "path",
					"description": "Unique id for item",
					"required": true,
					"type": "integer"
				},
				{
					"name": "name",
					"in": "formData",
					"description": "Name of item",
					"required": true,
					"type": "string"
				},
				{
					"name": "description",
					"in": "formData",
					"description": "Description of item",
					"required": true,
					"type": "string"
				}],
				"responses": {
					"200": {
						"description": "A successful response.",
						"schema": {
							"type": "array",
							"items": {
								"$ref": "#/definitions/item"
							}
						}
					}
				},
				"tags": ["cowquake"]
			},
			"delete": {
				"summary": "cowquake item",
				"description": "deletes a single cowquake item",
				"operationId": "deletecowquakeItem",
				"parameters": [{
					"name": "id",
					"in": "path",
					"description": "Unique id for item",
					"required": true,
					"type": "integer"
				}],
				"responses": {
					"200": {
						"description": "A successful response.",
						"schema": {
							"type": "array",
							"items": {
								"$ref": "#/definitions/item"
							}
						}
					}
				},
				"tags": ["cowquake"]
			}
		}
	},
	"definitions": {
		"item": {
			"properties": {
				"name": {
					"description": "The name of this item.",
					"type": "string"
				},
				"description": {
					"description": "The description of this item.",
					"type": "string"
				}
			}
		}
	}
}